LICENSE
MANIFEST.in
README.md
requirements.txt
setup.py
bk_notice_sdk/__init__.py
bk_notice_sdk/apps.py
bk_notice_sdk/config.py
bk_notice_sdk/urls.py
bk_notice_sdk/utils.py
bk_notice_sdk/views.py
bk_notice_sdk.egg-info/PKG-INFO
bk_notice_sdk.egg-info/SOURCES.txt
bk_notice_sdk.egg-info/dependency_links.txt
bk_notice_sdk.egg-info/requires.txt
bk_notice_sdk.egg-info/top_level.txt
bk_notice_sdk/management/__init__.py
bk_notice_sdk/management/commands/__init__.py
bk_notice_sdk/management/commands/register_application.py
bkapi/__init__.py
bkapi/bk_notice/__init__.py
bkapi/bk_notice/client.py
bkapi/bk_notice/shortcuts.py