Metadata-Version: 2.1
Name: bk-notice-sdk
Version: 1.3.0
Summary: A project for fetching and displaying announcement notifications.
Home-page: UNKNOWN
Author: blueking
Author-email: blueking@tencent.com
License: UNKNOWN
Platform: UNKNOWN
